interpretsr/__init__.py
interpretsr/mlp_sr.py
interpretsr/utils.py
interpretsr-1.0.2.dist-info/METADATA
interpretsr-1.0.2.dist-info/WHEEL
interpretsr-1.0.2.dist-info/top_level.txt
interpretsr-1.0.2.dist-info/RECORD
