Metadata-Version: 2.4
Name: interpretsr
Version: 1.0.2
Summary: Deep Learning Interpretability with Symbolic Regression.
Author: Liz Tan
Author-email: eszt2@cam.ac.uk
Classifier: Programming Language :: Python :: 3.11
Classifier: License :: OSI Approved :: MIT License
Classifier: Operating System :: OS Independent
Requires-Python: >=3.11
Requires-Dist: torch
Requires-Dist: pysr
Requires-Dist: numpy
Requires-Dist: pandas
Requires-Dist: scikit-learn
Requires-Dist: matplotlib
Requires-Dist: sympy
Dynamic: author
Dynamic: author-email
Dynamic: classifier
Dynamic: description
Dynamic: description-content-type
Dynamic: requires-dist
Dynamic: requires-python
Dynamic: summary
